vistutils/__init__.py
vistutils/decoratinator/__init__.py
vistutils/decoratinator/_abstract_decorator.py
vistutils/decoratinator/_add_child.py
vistutils/decoratinator/_add_parent.py
vistutils/decoratinator/_mid_class.py
vistutils/decoratinator/_who_dat.py
vistutils/ezdata/__init__.py
vistutils/ezdata/_ez_meta.py
vistutils/ezdata/_ez_namespace.py
vistutils/ezdata/_ez_types.py
vistutils/fields/__init__.py
vistutils/fields/_abstract_field.py
vistutils/fields/_break_point.py
vistutils/fields/_complex_field.py
vistutils/fields/_core_descriptor.py
vistutils/fields/_empty_field.py
vistutils/fields/_field.py
vistutils/fields/_field_box.py
vistutils/fields/_flag.py
vistutils/fields/_float_field.py
vistutils/fields/_immutable_decriptor.py
vistutils/fields/_int_field.py
vistutils/fields/_mutable_descriptor.py
vistutils/fields/_parse_name.py
vistutils/fields/_static_field.py
vistutils/fields/_sys_parse.py
vistutils/fields/_text_field.py
vistutils/fields/_typed_field.py
vistutils/fields/_unparse_args.py
vistutils/fields/_wait.py
vistutils/metas/__init__.py
vistutils/metas/_abstract_metaclass.py
vistutils/metas/_abstract_namespace.py
vistutils/metas/_base_namespace.py
vistutils/metas/_descriptor_namespace.py
vistutils/metas/_meta_descriptor.py
vistutils/metas/_type_names.py
vistutils/parse/__init__.py
vistutils/parse/_maybe.py
vistutils/parse/_search_key.py
vistutils/text/__init__.py
vistutils/text/_join_words.py
vistutils/text/_mono_space.py
vistutils/text/_string_list.py
vistutils/waitaminute/__init__.py
vistutils/waitaminute/_effort_exception.py
vistutils/waitaminute/_parsing_error.py
vistutils/waitaminute/_type_msg.py
vistutils/waitaminute/_wait_for_it.py
vistutils-0.1.51.dist-info/LICENSE
vistutils-0.1.51.dist-info/METADATA
vistutils-0.1.51.dist-info/WHEEL
vistutils-0.1.51.dist-info/top_level.txt
vistutils-0.1.51.dist-info/RECORD
